okpt/__init__.py
okpt/py.typed
okpt-0.0.1.dist-info/entry_points.txt
okpt-0.0.1.dist-info/LICENSE
okpt-0.0.1.dist-info/WHEEL
okpt-0.0.1.dist-info/METADATA
okpt-0.0.1.dist-info/RECORD
